{
    "name": "Aviansie",
    "levelRequired": 1,
    "itemsRequired": [
        "Ranged or Magic weapon"
    ],
    "itemsSuggested": [
        
    ],
    "attributes": [
        "None"
    ],
    "attackStyles": [
        "Ranged"
    ],
    "variants": [
        "Aviansie --lvl 69 --lvl 148",
        "Kree'arra --lvl 580",
        "Flight Kilisa --lvl 159",
        "Flockleader Geerin --lvl 149",
        "Wingman Skree --lvl 143"
    ],
    "masters": [
        "Krystilia",
        "Chaeldar",
        "Konar quo Maten",
        "Nieve",
        "Duradel"
    ],
    "variantLocations": {
        "Aviansie --lvl 69 --lvl 148": [
            "God Wars Dungeon",
            "Wilderness God Wars Dungeon"
        ],
        "Kree'arra --lvl 580": [
            "God Wars Dungeon"
        ],
        "Flight Kilisa --lvl 159": [
            "God Wars Dungeon"
        ],
        "Flockleader Geerin --lvl 149": [
            "God Wars Dungeon"
        ],
        "Wingman Skree --lvl 143": [
            "God Wars Dungeon"
        ]
    }
}
