{
    "name": "Black demon",
    "levelRequired": 80,
    "itemsRequired": [
        
    ],
    "itemsSuggested": [
        
    ],
    "attributes": [
        "Demon"
    ],
    "attackStyles": [
        "Melee"
    ],
    "variants": [
        "Black demon --lvl 172 --lvl 188",
        "Demonic gorilla --lvl 275",
        "Skotizo --lvl 321"
    ],
    "masters": [
        "Krystilia",
        "Chaeldar",
        "Konar quo Maten",
        "Nieve",
        "Duradel"
    ],
    "variantLocations": {
        "Black demon --lvl 172 --lvl 188": [
            "Taverley Dungeon",
            "Edgeville Dungeon",
            "Brimhaven Dungeon",
            "Catacombs of Kourend",
            "Charred Dungeon",
            "Chasm of Fire",
            "Wilderness Slayer Cave"
        ],
        "Demonic gorilla --lvl 275": [
            "Crash Site Cavern"
        ],
        "Skotizo --lvl 321": [
            "Catacombs of Kourend"
        ]
    }
}
