{
    "name": "Cave crawler",
    "levelRequired": 10,
    "itemsRequired": [
        
    ],
    "itemsSuggested": [
        "Antipoison"
    ],
    "attributes": [
        "None"
    ],
    "attackStyles": [
        "Melee",
        "Poison"
    ],
    "variants": [
        "Cave crawler --lvl 23"
    ],
    "masters": [
        "Turael",
        "Mazchna",
        "Spria"
    ],
    "variantLocations": {
        "Cave crawler --lvl 23": [
            "Fremennik Slayer Dungeon",
            "Lumbridge Swamp Caves",
            "Dorgesh-Kaan South Dungeon",
            "Ruins of Tapouik"
        ]
    }
}
