{
    "name": "Harpie bug swarm",
    "levelRequired": 33,
    "itemsRequired": [
        "Lit bug lantern"
    ],
    "itemsSuggested": [
        
    ],
    "attributes": [
        "None"
    ],
    "attackStyles": [
        "Melee"
    ],
    "variants": [
        "Harpie bug swarm --lvl 46"
    ],
    "masters": [
        "Vannaka"
    ],
    "variantLocations": {
        "Harpie bug swarm --lvl 46": [
            "NE of Tai Bwo Wannai",
            "East of Colossal Wyrm Remains"
        ]
    }
}
